aqib1lib/__init__.py
aqib1lib/hello.py
aqib1lib-0.0.1.dist-info/METADATA
aqib1lib-0.0.1.dist-info/WHEEL
aqib1lib-0.0.1.dist-info/top_level.txt
aqib1lib-0.0.1.dist-info/RECORD
